audiomatic/__init__.py
audiomatic/client.py
audiomatic-0.1.4.dist-info/LICENSE
audiomatic-0.1.4.dist-info/METADATA
audiomatic-0.1.4.dist-info/WHEEL
audiomatic-0.1.4.dist-info/top_level.txt
audiomatic-0.1.4.dist-info/RECORD
