Metadata-Version: 2.2
Name: audiomatic
Version: 0.1.4
Summary: The official Python client for the Audiomatic API
Author-email: Audiomatic <support@audiomatic.app>
License: MIT License
Project-URL: Homepage, https://github.com/AudiomaticInc/audiomatic-python
Keywords: audiomatic,translation,video,api,client
Requires-Python: >=3.9
License-File: LICENSE
Requires-Dist: filetype>=1.2.0
Requires-Dist: imageio-ffmpeg>=0.5.1
Requires-Dist: requests>=2.32.3
Requires-Dist: urllib3<2.0.0
